LICENSE
MANIFEST.in
README.rst
setup.py
niaopendata/__init__.py
niaopendata/api.py
niaopendata/members.py
niaopendata/organisations.py
niaopendata.egg-info/PKG-INFO
niaopendata.egg-info/SOURCES.txt
niaopendata.egg-info/dependency_links.txt
niaopendata.egg-info/not-zip-safe
niaopendata.egg-info/pbr.json
niaopendata.egg-info/requires.txt
niaopendata.egg-info/top_level.txt