Metadata-Version: 1.1
Name: niaopendata
Version: 0.0.1
Summary: niaopendata is a Python client for the Northern Ireland Assembly Open Data API
Home-page: https://github.com/paddycarey/niaopendata
Author: Patrick Carey
Author-email: paddy@wackwack.co.uk
License: MIT
Keywords: NI Northern Ireland Assembly Open Data
Platform: UNKNOWN
Classifier: Development Status :: 3 - Alpha
Classifier: Intended Audience :: Developers
Classifier: License :: OSI Approved :: MIT License
Classifier: Natural Language :: English
Classifier: Programming Language :: Python :: 2
Classifier: Programming Language :: Python :: 2.6
Classifier: Programming Language :: Python :: 2.7
Classifier: Programming Language :: Python :: 3
Classifier: Programming Language :: Python :: 3.3
Classifier: Programming Language :: Python :: 3.4
Classifier: Programming Language :: Python :: Implementation :: CPython
Classifier: Programming Language :: Python :: Implementation :: PyPy
